pymote3/__init__.py
pymote3/algorithm.py
pymote3/channeltype.py
pymote3/environment.py
pymote3/logger.py
pymote3/message.py
pymote3/network.py
pymote3/networkgenerator.py
pymote3/node.py
pymote3/npickle.py
pymote3/release.py
pymote3/sensor.py
pymote3/simulation.py
pymote3/algorithms/__init__.py
pymote3/algorithms/broadcast.py
pymote3/algorithms/dft.py
pymote3/algorithms/readsensors.py
pymote3/algorithms/niculescu2003/__init__.py
pymote3/algorithms/niculescu2003/dvhop.py
pymote3/algorithms/niculescu2003/floodingupdate.py
pymote3/algorithms/niculescu2003/trilaterate.py
pymote3/algorithms/santoro2007/__init__.py
pymote3/algorithms/santoro2007/traversal.py
pymote3/algorithms/santoro2007/yoyo.py
pymote3/bmo/__init__.py
pymote3/bmo/algorithms/__init__.py
pymote3/bmo/algorithms/routing.py
pymote3/bmo/algorithms/saturation.py
pymote3/bmo/algorithms/shout.py
pymote3/bmo/sensors/__init__.py
pymote3/bmo/sensors/temperature.py
pymote3/conf/__init__.py
pymote3/conf/global_settings.py
pymote3/conf/ipython/__init__.py
pymote3/conf/ipython/ipython_config.py
pymote3/conf/ipython/ipython_notebook_config.py
pymote3/gui/__init__.py
pymote3/gui/dictionarytreemodel.py
pymote3/gui/icons_rc.py
pymote3/gui/qtreeview_example.py
pymote3/gui/simulation.ui.py
pymote3/gui/simulationgui.py
pymote3/gui/simulationui.py
pymote3/scripts/__init__.py
pymote3/scripts/ipymote3.py
pymote3/tests/__init__.py
pymote3/tests/test_algorithm.py
pymote3/tests/test_network.py
pymote3/tests/test_networkgenerator.py
pymote3/tests/test_sensor.py
pymote3/tests/test_stitchers.py
pymote3/tests/algorithms/__init__.py
pymote3/tests/algorithms/santoro2007/__init__.py
pymote3/tests/algorithms/santoro2007/test_yoyo.py
pymote3/utils/__init__.py
pymote3/utils/helpers.py
pymote3/utils/tree.py
pymote3/utils/visualization.py
pymote3/utils/localization/__init__.py
pymote3/utils/localization/aoastitcher.py
pymote3/utils/localization/basestitcher.py
pymote3/utils/localization/diststitcher.py
pymote3/utils/localization/helpers.py
Pymote3-0.2.3.dist-info/METADATA
Pymote3-0.2.3.dist-info/WHEEL
Pymote3-0.2.3.dist-info/entry_points.txt
Pymote3-0.2.3.dist-info/top_level.txt
Pymote3-0.2.3.dist-info/RECORD
